steam_workshop/__init__.py
steam_workshop/collection.py
steam_workshop-0.0.1.dist-info/METADATA
steam_workshop-0.0.1.dist-info/WHEEL
steam_workshop-0.0.1.dist-info/top_level.txt
steam_workshop-0.0.1.dist-info/RECORD
