Metadata-Version: 1.0
Name: steam-workshop
Version: 0.0.1
Summary: A package to scrape Collection information from the Steam Workshop.
Home-page: https://github.com/Fakas/steam-workshop
Author: Matthew Cazaly
Author-email: UNKNOWN
License: UNKNOWN
Platform: UNKNOWN
